axado/__init__.py
axado/api.py
axado/settings.py
axado/tests.py
axado-0.1.dist-info/DESCRIPTION.rst
axado-0.1.dist-info/METADATA
axado-0.1.dist-info/RECORD
axado-0.1.dist-info/WHEEL
axado-0.1.dist-info/metadata.json
axado-0.1.dist-info/top_level.txt
