Metadata-Version: 2.0
Name: axado
Version: 0.1
Summary: Python bindings to the Axado API (https://developers.axado.com.br/)
Home-page: https://github.com/scardine/python-axado
Author: Paulo Scardine
Author-email: paulos@xtend.com.br
License: UNKNOWN
Download-URL: https://github.com/scardine/python-axado/archive/0.1.tar.gz
Keywords: axado,api
Platform: UNKNOWN
Requires-Dist: requests
